localStoragePy/__init__.py
localStoragePy/storage_backends.py
localStoragePy-0.2.3.dist-info/LICENSE
localStoragePy-0.2.3.dist-info/METADATA
localStoragePy-0.2.3.dist-info/WHEEL
localStoragePy-0.2.3.dist-info/top_level.txt
localStoragePy-0.2.3.dist-info/RECORD
