Metadata-Version: 2.1
Name: localStoragePy
Version: 0.2.3
Summary: A familiar API from the Web, adapted to storing data locally with Python.
Home-page: http://github.com/jkelol111/localStoragePy
Author: Nguyen Thanh Nam (jkelol111)
Author-email: jkelol111@gmail.com
License: MIT
Platform: UNKNOWN
Classifier: Programming Language :: Python :: 3
Classifier: License :: OSI Approved :: MIT License
Classifier: Operating System :: OS Independent
